toon_parser_async/__init__.py
toon_parser_async-0.1.4.dist-info/licenses/LICENSE
toon_parser_async-0.1.4.dist-info/METADATA
toon_parser_async-0.1.4.dist-info/WHEEL
toon_parser_async-0.1.4.dist-info/top_level.txt
toon_parser_async-0.1.4.dist-info/RECORD
