Metadata-Version: 2.4
Name: toon-parser-async
Version: 0.1.4
Summary: Async wrapper for toon-parser - High-performance TOON format parser
Author-email: magi8101 <sharmamagi0@gmail.com>
License-Expression: MIT
Project-URL: Homepage, https://github.com/magi8101/toon-parser
Project-URL: Repository, https://github.com/magi8101/toon-parser
Project-URL: Documentation, https://github.com/magi8101/toon-parser#readme
Keywords: toon,async,asyncio,parser,serialization
Classifier: Development Status :: 4 - Beta
Classifier: Intended Audience :: Developers
Classifier: Programming Language :: Python :: 3
Classifier: Programming Language :: Python :: 3.8
Classifier: Programming Language :: Python :: 3.9
Classifier: Programming Language :: Python :: 3.10
Classifier: Programming Language :: Python :: 3.11
Classifier: Programming Language :: Python :: 3.12
Classifier: Framework :: AsyncIO
Classifier: Topic :: Software Development :: Libraries :: Python Modules
Classifier: Topic :: Text Processing
Requires-Python: >=3.8
License-File: LICENSE
Requires-Dist: toon-parser>=0.1.2
Dynamic: license-file
